block_tracing.py
block_tracing-1.0.1.dist-info/LICENSE
block_tracing-1.0.1.dist-info/METADATA
block_tracing-1.0.1.dist-info/WHEEL
block_tracing-1.0.1.dist-info/top_level.txt
block_tracing-1.0.1.dist-info/RECORD
