Metadata-Version: 2.1
Name: block-tracing
Version: 1.0.1
Summary: Protect process memory
Home-page: https://github.com/rianhunter/block_tracing
Author: Rian Hunter
Author-email: rian@alum.mit.edu
License: MIT
Platform: UNKNOWN
